{
	"name": "gd32v",
	"title": "gd32v",
	"version": "1.3.0",
	"description": "The GigaDevice GD32V device is a 32-bit general-purpose microcontroller based on the RISC-V core with an impressive balance of processing power, reduced power consumption and peripheral set.",
	"homepage": "https://www.gigadevice.com/products/microcontrollers/gd32/risc-v/",
	"keywords": [
		"dev-platform",
		"GigaDevice",
		"GD32V",
		"RISC-V",
		"Sipeed",
		"Longan",
		"32bit"
	],
	"license": "Apache-2.0",
	"engines": {
		"platformio": "^6"
	},
	"repository": {
		"type": "git",
		"url": "https://github.com/AStr347/platform-gd32v"
	},
	"authors": [
		{
			"name": "Sipeed",
			"email": "support@sipeed.com",
			"url": "https://www.sipeed.com"
		},
		{
			"name": "AStr347",
			"url": "https://github.com/AStr347"
		}
	],
	"packages": {
		"framework-arduino-gd32v": {
			"type": "framework",
			"system": "*",
			"version": "file:///root/.platformio/platforms/gd32v/dist/framework-arduino-gd32v-demo-0.1.1.tar.gz"
		},
		"framework-gd32vf103-sdk": {
			"type": "framework",
			"system": "*",
			"version": "file:///root/.platformio/platforms/gd32v/dist/framework-gd32vf103-sdk-v1.0.0.tar.gz"
		},
		"toolchain-gd32v-linux_x86_64": {
			"type": "toolchain",
			"system": "linux_x86_64",
			"version": "file:///root/.platformio/platforms/gd32v/dist/toolchain-gd32v-v9.2.0-linux.tar.gz"
		},
		"toolchain-gd32v-windows": {
			"type": "toolchain",
			"system": [
				"windows_x86",
				"windows_amd64"
			],
			"version": "file:///root/.platformio/platforms/gd32v/dist/toolchain-gd32v-v9.2.0-win.tar.gz"
		},
		"tool-openocd-gd32v-linux_x86_64": {
			"type": "uploader",
			"system": "linux_x86_64",
			"version": "file:///root/.platformio/platforms/gd32v/dist/tool-openocd-gd32v-v0.1.1-linux.tar.gz"
		},
		"tool-openocd-gd32v-windows": {
			"type": "uploader",
			"system": [
				"windows_x86",
				"windows_amd64"
			],
			"version": "file:///root/.platformio/platforms/gd32v/dist/tool-openocd-gd32v-v0.1.1-win.tar.gz"
		},
		"tool-gd32vflash-linux_x86_64": {
			"type": "uploader",
			"system": "linux_x86_64",
			"version": "file:///root/.platformio/platforms/gd32v/dist/tool-gd32vflash-v0.1.0-linux.tar.gz"
		},
		"tool-gd32vflash-windows": {
			"type": "uploader",
			"system": [
				"windows_x86",
				"windows_amd64"
			],
			"version": "file:///root/.platformio/platforms/gd32v/dist/tool-gd32vflash-v0.1.0-win.tar.gz"
		}
	}
}